ragents/__init__.py
ragents/cli.py
ragents/agents/__init__.py
ragents/agents/base.py
ragents/agents/decision_tree.py
ragents/agents/graph_planner.py
ragents/agents/langgraph_base.py
ragents/agents/langgraph_multi_agent.py
ragents/agents/langgraph_react.py
ragents/agents/react_agent.py
ragents/config/__init__.py
ragents/config/base.py
ragents/config/environment.py
ragents/config/rag_config.py
ragents/deployment/__init__.py
ragents/deployment/litserve_server.py
ragents/evaluation/__init__.py
ragents/evaluation/datasets.py
ragents/evaluation/evaluator.py
ragents/evaluation/metrics.py
ragents/evaluation/types.py
ragents/frontend/templates/dashboard.html
ragents/guardrails/__init__.py
ragents/guardrails/base.py
ragents/ingestion/__init__.py
ragents/ingestion/config.py
ragents/ingestion/extractors.py
ragents/ingestion/monitoring.py
ragents/ingestion/pipeline.py
ragents/ingestion/processors.py
ragents/ingestion/validators.py
ragents/llm/__init__.py
ragents/llm/client.py
ragents/llm/types.py
ragents/logical_llm/__init__.py
ragents/logical_llm/constraint_engine.py
ragents/logical_llm/domain_definitions.py
ragents/logical_llm/integration.py
ragents/logical_llm/logic_patterns.py
ragents/logical_llm/logical_reasoner.py
ragents/logical_llm/models.py
ragents/logical_llm/query_clarifier.py
ragents/logical_llm/symbolic_solver.py
ragents/observability/__init__.py
ragents/observability/metrics.py
ragents/observability/openinference.py
ragents/observability/structured_logging.py
ragents/observability/tracer.py
ragents/query_rewriting/__init__.py
ragents/query_rewriting/base.py
ragents/query_rewriting/evaluator.py
ragents/query_rewriting/interactive.py
ragents/query_rewriting/optimizer.py
ragents/query_rewriting/strategies.py
ragents/rag/__init__.py
ragents/rag/document_store.py
ragents/rag/engine.py
ragents/rag/retriever.py
ragents/rag/types.py
ragents/reranking/__init__.py
ragents/reranking/autocut.py
ragents/reranking/base.py
ragents/reranking/config.py
ragents-0.1.3.dist-info/METADATA
ragents-0.1.3.dist-info/WHEEL
ragents-0.1.3.dist-info/entry_points.txt
ragents-0.1.3.dist-info/licenses/LICENSE
ragents-0.1.3.dist-info/RECORD
