Metadata-Version: 2.4
Name: RAGents
Version: 0.1.3
Summary: Production-ready agentic RAG framework featuring intelligent decision trees, Logic-LLM integration, multimodal processing, and enterprise observability
License-File: LICENSE
Requires-Python: >=3.10
Requires-Dist: aiofiles>=23.0.0
Requires-Dist: anthropic>=0.7.0
Requires-Dist: beautifulsoup4>=4.12.0
Requires-Dist: chromadb>=0.4.0
Requires-Dist: click>=8.0.0
Requires-Dist: fastapi>=0.100.0
Requires-Dist: httpx>=0.24.0
Requires-Dist: instructor>=1.6.0
Requires-Dist: jinja2>=3.0.0
Requires-Dist: langchain-core>=0.1.0
Requires-Dist: langchain-text-splitters>=0.0.1
Requires-Dist: langgraph>=0.2.0
Requires-Dist: litserve>=0.2.0
Requires-Dist: markdownify>=0.11.0
Requires-Dist: mkdocs>=1.6.1
Requires-Dist: numpy>=1.24.0
Requires-Dist: openai>=1.0.0
Requires-Dist: openpyxl>=3.1.0
Requires-Dist: pandas>=2.0.0
Requires-Dist: pillow>=10.0.0
Requires-Dist: prometheus-client>=0.16.0
Requires-Dist: psutil>=5.9.0
Requires-Dist: pydantic>=2.0.0
Requires-Dist: pymupdf>=1.23.0
Requires-Dist: python-docx>=0.8.11
Requires-Dist: python-multipart>=0.0.6
Requires-Dist: sentence-transformers>=2.2.0
Requires-Dist: tiktoken>=0.5.0
Requires-Dist: uvicorn>=0.20.0
Provides-Extra: all
Requires-Dist: asyncpg>=0.28.0; extra == 'all'
Requires-Dist: docker>=6.0.0; extra == 'all'
Requires-Dist: elasticsearch>=8.0.0; extra == 'all'
Requires-Dist: gunicorn>=21.0.0; extra == 'all'
Requires-Dist: kfp>=2.0.0; extra == 'all'
Requires-Dist: kubernetes>=28.0.0; extra == 'all'
Requires-Dist: litserve>=0.2.0; extra == 'all'
Requires-Dist: opentelemetry-api>=1.20.0; extra == 'all'
Requires-Dist: opentelemetry-sdk>=1.20.0; extra == 'all'
Requires-Dist: prometheus-client>=0.16.0; extra == 'all'
Requires-Dist: torch>=2.0.0; extra == 'all'
Requires-Dist: transformers>=4.35.0; extra == 'all'
Requires-Dist: weaviate-client>=4.0.0; extra == 'all'
Provides-Extra: all-vector-stores
Requires-Dist: asyncpg>=0.28.0; extra == 'all-vector-stores'
Requires-Dist: elasticsearch>=8.0.0; extra == 'all-vector-stores'
Requires-Dist: weaviate-client>=4.0.0; extra == 'all-vector-stores'
Provides-Extra: deployment
Requires-Dist: docker>=6.0.0; extra == 'deployment'
Requires-Dist: grafana-client>=3.5.0; extra == 'deployment'
Requires-Dist: gunicorn>=21.0.0; extra == 'deployment'
Requires-Dist: kfp>=2.0.0; extra == 'deployment'
Requires-Dist: kubernetes>=28.0.0; extra == 'deployment'
Requires-Dist: litserve>=0.2.0; extra == 'deployment'
Requires-Dist: prometheus-client>=0.16.0; extra == 'deployment'
Provides-Extra: dev
Requires-Dist: bandit[toml]>=1.7.0; extra == 'dev'
Requires-Dist: black>=23.0.0; extra == 'dev'
Requires-Dist: mypy>=1.5.0; extra == 'dev'
Requires-Dist: pre-commit>=3.0.0; extra == 'dev'
Requires-Dist: pytest-asyncio>=0.21.0; extra == 'dev'
Requires-Dist: pytest>=7.0.0; extra == 'dev'
Requires-Dist: ruff>=0.1.0; extra == 'dev'
Requires-Dist: safety>=2.3.0; extra == 'dev'
Provides-Extra: docs
Requires-Dist: mkdocs-material>=9.0.0; extra == 'docs'
Requires-Dist: mkdocs>=1.5.0; extra == 'docs'
Requires-Dist: mkdocstrings[python]>=0.24.0; extra == 'docs'
Requires-Dist: pymdown-extensions>=10.0.0; extra == 'docs'
Provides-Extra: elasticsearch
Requires-Dist: elasticsearch>=8.0.0; extra == 'elasticsearch'
Provides-Extra: evaluation
Requires-Dist: ragas>=0.1.0; extra == 'evaluation'
Provides-Extra: observability
Requires-Dist: opentelemetry-api>=1.20.0; extra == 'observability'
Requires-Dist: opentelemetry-sdk>=1.20.0; extra == 'observability'
Provides-Extra: pgvector
Requires-Dist: asyncpg>=0.28.0; extra == 'pgvector'
Provides-Extra: vision
Requires-Dist: torch>=2.0.0; extra == 'vision'
Requires-Dist: transformers>=4.35.0; extra == 'vision'
Provides-Extra: weaviate
Requires-Dist: weaviate-client>=4.0.0; extra == 'weaviate'
